README.md
setup.cfg
setup.py
pgstatus/__init__.py
pgstatus/configuration.py
pgstatus/database.py
pgstatus/server.py
pgstatus.egg-info/PKG-INFO
pgstatus.egg-info/SOURCES.txt
pgstatus.egg-info/dependency_links.txt
pgstatus.egg-info/entry_points.txt
pgstatus.egg-info/requires.txt
pgstatus.egg-info/top_level.txt
pgstatus/bin/__init__.py
pgstatus/bin/pgstatus_daemon.py