Metadata-Version: 1.2
Name: pgstatus
Version: 1.1.3
Summary: HTTP server to check postgresql server status
Home-page: https://github.com/hile/pgstatus/
Author: Ilkka Tuohela
Author-email: ilkka.tuohela@codento.com
License: PSF
Keywords: postgresql haproxy status check tools
Platform: UNKNOWN
Requires-Python: >=2.7
